ucsmsdk/__init__.py
ucsmsdk/ucsbasetype.py
ucsmsdk/ucsconstants.py
ucsmsdk/ucscore.py
ucsmsdk/ucscoremeta.py
ucsmsdk/ucscoreutils.py
ucsmsdk/ucsdriver.py
ucsmsdk/ucseventhandler.py
ucsmsdk/ucsexception.py
ucsmsdk/ucsfilter.py
ucsmsdk/ucsfiltertype.py
ucsmsdk/ucsgenutils.py
ucsmsdk/ucshandle.py
ucsmsdk/ucsmeta.py
ucsmsdk/ucsmethod.py
ucsmsdk/ucsmethodfactory.py
ucsmsdk/ucsmo.py
ucsmsdk/ucssession.py
ucsmsdk/ucsxmlcodec.py
ucsmsdk/methodmeta/AaaChangeSelfPasswordMeta.py
ucsmsdk/methodmeta/AaaCheckComputeAuthTokenMeta.py
ucsmsdk/methodmeta/AaaCheckComputeExtAccessMeta.py
ucsmsdk/methodmeta/AaaGetAuthTokenClientMeta.py
ucsmsdk/methodmeta/AaaGetKVMLaunchUrlMeta.py
ucsmsdk/methodmeta/AaaGetNComputeAuthTokenByDnMeta.py
ucsmsdk/methodmeta/AaaKeepAliveMeta.py
ucsmsdk/methodmeta/AaaLoginMeta.py
ucsmsdk/methodmeta/AaaLogoutMeta.py
ucsmsdk/methodmeta/AaaRefreshMeta.py
ucsmsdk/methodmeta/AaaTokenLoginMeta.py
ucsmsdk/methodmeta/AaaTokenRefreshMeta.py
ucsmsdk/methodmeta/ApeBootPnuOsMeta.py
ucsmsdk/methodmeta/ApeConfigureCMCLIFMeta.py
ucsmsdk/methodmeta/ApeCreateHVVnicMeta.py
ucsmsdk/methodmeta/ApeCreateSfishMeta.py
ucsmsdk/methodmeta/ApeCreateVMVnicMeta.py
ucsmsdk/methodmeta/ApeDeleteHVVnicMeta.py
ucsmsdk/methodmeta/ApeDeleteSfishMeta.py
ucsmsdk/methodmeta/ApeDeleteVMVnicMeta.py
ucsmsdk/methodmeta/ApeGetAdaptorConnectivityMeta.py
ucsmsdk/methodmeta/ApeGetNextIdMeta.py
ucsmsdk/methodmeta/ApeGetPnuOSInventoryMeta.py
ucsmsdk/methodmeta/ApeGetServerFromIpMeta.py
ucsmsdk/methodmeta/ApeGetSwitchApeFruMeta.py
ucsmsdk/methodmeta/ApeInjectStimuliMeta.py
ucsmsdk/methodmeta/ApeInsertNewChassisMeta.py
ucsmsdk/methodmeta/ApeInsertNewFexMeta.py
ucsmsdk/methodmeta/ApeInsertNewRackMeta.py
ucsmsdk/methodmeta/ApeIssueAdaptorIdMeta.py
ucsmsdk/methodmeta/ApeIssueChassisIdMeta.py
ucsmsdk/methodmeta/ApeIssueFexIdMeta.py
ucsmsdk/methodmeta/ApeIssueRackIdMeta.py
ucsmsdk/methodmeta/ApeMcGetAttributeDataMeta.py
ucsmsdk-0.9.1.0.dist-info/DESCRIPTION.rst
ucsmsdk-0.9.1.0.dist-info/METADATA
ucsmsdk-0.9.1.0.dist-info/RECORD
ucsmsdk-0.9.1.0.dist-info/WHEEL
ucsmsdk-0.9.1.0.dist-info/metadata.json
ucsmsdk-0.9.1.0.dist-info/top_level.txt
