Metadata-Version: 2.0
Name: ucsmsdk
Version: 0.9.1.0
Summary: Python SDK for Cisco UCS
Home-page: https://github.com/CiscoUcs/ucsmsdk
Author: Cisco Systems Inc
Author-email: ucs-python@cisco.com
License: http://www.apache.org/licenses/LICENSE-2.0
Keywords: ucsmsdk
Platform: UNKNOWN
Classifier: Development Status :: 4 - Beta
Classifier: Intended Audience :: Developers
Classifier: License :: OSI Approved :: Apache Software License
Classifier: Natural Language :: English
Classifier: Programming Language :: Python :: 2
Classifier: Programming Language :: Python :: 2.6
Classifier: Programming Language :: Python :: 2.7
Classifier: Programming Language :: Python :: 3
Classifier: Programming Language :: Python :: 3.3
Classifier: Programming Language :: Python :: 3.4
Requires-Dist: pyparsing
Provides-Extra: docs
Requires-Dist: sphinx (<1.3); extra == 'docs'
Requires-Dist: sphinx-rtd-theme; extra == 'docs'
Requires-Dist: sphinxcontrib-napoleon; extra == 'docs'
Provides-Extra: ssl
Requires-Dist: pyOpenSSL; extra == 'ssl'
